gfmtoc/__init__.py
gfmtoc/gfmtoc.py
gfmtoc-1.1.1.dist-info/DESCRIPTION.rst
gfmtoc-1.1.1.dist-info/METADATA
gfmtoc-1.1.1.dist-info/RECORD
gfmtoc-1.1.1.dist-info/WHEEL
gfmtoc-1.1.1.dist-info/entry_points.txt
gfmtoc-1.1.1.dist-info/metadata.json
gfmtoc-1.1.1.dist-info/top_level.txt
